pygro/__init__.py
pygro/default_metrics/Kerr-BL.metric
pygro/default_metrics/__init__.py
pygro/geodesic.py
pygro/geodesic_engine.py
pygro/integrators.py
pygro/interpolators.py
pygro/metric_engine.py
pygro/observer.py
pygro/orbit.py
pygro/utils/__init__.py
pygro/utils/constants.py
pygro/utils/kepler.py
pygro/utils/pi_formatter.py
pygro/utils/rotations.py
pygro-1.0.2.dist-info/LICENSE.txt
pygro-1.0.2.dist-info/METADATA
pygro-1.0.2.dist-info/WHEEL
pygro-1.0.2.dist-info/RECORD
