Metadata-Version: 2.3
Name: pygro
Version: 1.0.2
Summary: A Python Integrator for General Relativistic Orbits
License: GNU GPL-3.0 license
Author: Riccardo Della Monica
Author-email: dellamonicariccardo@gmail.com
Requires-Python: >=3.10
Classifier: License :: Other/Proprietary License
Classifier: Programming Language :: Python :: 3
Classifier: Programming Language :: Python :: 3.10
Classifier: Programming Language :: Python :: 3.11
Classifier: Programming Language :: Python :: 3.12
Classifier: Programming Language :: Python :: 3.13
Requires-Dist: numpy (>=2.2.2)
Requires-Dist: scipy (>=1.15.1)
Requires-Dist: sympy (>=1.11.1)
